Metadata-Version: 2.1
Name: video-de-ferramentas-2023
Version: 1.0
Summary: Este pacote irá fornecer informações de processamento de vídeos
Author: Wilker
Author-email: teste@gmail.com
Keywords: Camera,Video,Processamento
License-File: license.txt
